[
  {
    "name": "0 min",
    "Soudidou92i": 0,
    "FRShark110": 0,
    "king of terra": 0,
    "Ezveeee": 0,
    "Bleudywind": 0
  },
  {
    "name": "5 min",
    "Soudidou92i": -7,
    "FRShark110": -392,
    "king of terra": -361,
    "Ezveeee": 332,
    "Bleudywind": -558
  },
  {
    "name": "10 min",
    "Soudidou92i": 52,
    "FRShark110": -1627,
    "king of terra": -387,
    "Ezveeee": 1032,
    "Bleudywind": -242
  },
  {
    "name": "15 min",
    "Soudidou92i": -582,
    "FRShark110": -2140,
    "king of terra": -659,
    "Ezveeee": 2559,
    "Bleudywind": -388
  },
  {
    "name": "20 min",
    "Soudidou92i": -653,
    "FRShark110": -2755,
    "king of terra": -26,
    "Ezveeee": 2846,
    "Bleudywind": -986
  },
  {
    "name": "25 min",
    "Soudidou92i": -1067,
    "FRShark110": -4418,
    "king of terra": -620,
    "Ezveeee": 3733,
    "Bleudywind": -941
  },
  {
    "name": "30 min",
    "Soudidou92i": -2750,
    "FRShark110": -5538,
    "king of terra": -212,
    "Ezveeee": 5208,
    "Bleudywind": -1755
  },
  {
    "name": "35 min",
    "Soudidou92i": -1707,
    "FRShark110": -7888,
    "king of terra": 188,
    "Ezveeee": 6331,
    "Bleudywind": -2001
  }
]